{
  "$schema": "https://raw.githubusercontent.com/Azure/bicep/main/src/Bicep.Core/Configuration/bicepconfig.schema.json",
  "analyzers": {
    "core": {
      "enabled": true,
      "verbose": true,
      "rules": {
        "no-hardcoded-env-urls": {
          "level": "warning"
        },
        "no-unused-params": {
          "level": "warning"
        },
        "no-unused-vars": {
          "level": "warning"
        },
        "prefer-interpolation": {
          "level": "warning"
        },
        "secure-parameter-default": {
          "level": "error"
        },
        "simplify-interpolation": {
          "level": "warning"
        },
        "protect-commandtoexecute-secrets": {
          "level": "error"
        },
        "use-stable-vm-image": {
          "level": "warning"
        },
        "explicit-values-for-loc-params": {
          "level": "warning"
        },
        "no-unnecessary-dependson": {
          "level": "warning"
        },
        "use-secure-value-for-secure-inputs": {
          "level": "error"
        },
        "outputs-should-not-contain-secrets": {
          "level": "error"
        }
      }
    }
  },
  "formatting": {
    "indentKind": "Space",
    "indentSize": 2,
    "insertFinalNewline": true
  },
  "experimentalFeaturesEnabled": {
    "symbolicNameCodegen": true,
    "extensibility": false,
    "resourceTypedParamsAndOutputs": true
  }
}
